vit4elm/__init__.py
vit4elm/data_processor.py
vit4elm/datasets.py
vit4elm/trainer.py
vit4elm-1.3.4.dist-info/LICENSE
vit4elm-1.3.4.dist-info/METADATA
vit4elm-1.3.4.dist-info/WHEEL
vit4elm-1.3.4.dist-info/top_level.txt
vit4elm-1.3.4.dist-info/RECORD
