Metadata-Version: 2.1
Name: vit4elm
Version: 1.3.4
Summary: Vision Transformers for Exotic Lattice Models
Author: Adam Sabra
License: UNKNOWN
Platform: UNKNOWN
Classifier: Programming Language :: Python :: 3
Classifier: License :: OSI Approved :: MIT License
Requires-Python: >=3.8
License-File: LICENSE
Requires-Dist: scikit-learn
Requires-Dist: numpy
Requires-Dist: matplotlib
Requires-Dist: pandas
Requires-Dist: transformers
Requires-Dist: datasets
Requires-Dist: torch
Requires-Dist: torchvision
Requires-Dist: pillow
Requires-Dist: twine
